django_admin_flexlist/__init__.py
django_admin_flexlist/admin.py
django_admin_flexlist/apps.py
django_admin_flexlist/models.py
django_admin_flexlist/stores.py
django_admin_flexlist/urls.py
django_admin_flexlist/utils.py
django_admin_flexlist/views.py
django_admin_flexlist/migrations/0001_initial.py
django_admin_flexlist/migrations/__init__.py
django_admin_flexlist/services/__init__.py
django_admin_flexlist/services/app_model_list.py
django_admin_flexlist/services/list_display.py
django_admin_flexlist/static/django_admin_flexlist/css/colors.css
django_admin_flexlist/static/django_admin_flexlist/css/edit_layout_form.css
django_admin_flexlist/templates/django_admin_flexlist/app_index.html
django_admin_flexlist/templates/django_admin_flexlist/app_index_actions.html
django_admin_flexlist/templates/django_admin_flexlist/app_index_content.html
django_admin_flexlist/templates/django_admin_flexlist/app_index_head.html
django_admin_flexlist/templates/django_admin_flexlist/app_index_script.html
django_admin_flexlist/templates/django_admin_flexlist/change_list.html
django_admin_flexlist/templates/django_admin_flexlist/change_list_actions.html
django_admin_flexlist/templates/django_admin_flexlist/change_list_content.html
django_admin_flexlist/templates/django_admin_flexlist/change_list_head.html
django_admin_flexlist/templates/django_admin_flexlist/index.html
django_admin_flexlist/templates/django_admin_flexlist/index_actions.html
django_admin_flexlist/templates/django_admin_flexlist/index_content.html
django_admin_flexlist/templates/django_admin_flexlist/index_head.html
django_admin_flexlist/templates/django_admin_flexlist/index_script.html
django_admin_flexlist/templates/django_admin_flexlist/components/edit_layout_button_index.html
django_admin_flexlist/templates/django_admin_flexlist/components/edit_layout_button_index_script.html
django_admin_flexlist/templates/django_admin_flexlist/components/edit_layout_form.html
django_admin_flexlist-1.0.4.dist-info/licenses/LICENSE
django_admin_flexlist-1.0.4.dist-info/METADATA
django_admin_flexlist-1.0.4.dist-info/WHEEL
django_admin_flexlist-1.0.4.dist-info/top_level.txt
django_admin_flexlist-1.0.4.dist-info/RECORD
