Metadata-Version: 2.4
Name: django-admin-flexlist
Version: 1.0.4
Summary: A Django extension that allows users to reorder and toggle visibility of admin list view, app index, and dashboard elements
Author: rafael-frs-a
License: Copyright 2025 rafael-frs-a
Project-URL: Homepage, https://github.com/rafael-frs-a/django-admin-flexlist
Project-URL: Documentation, https://github.com/rafael-frs-a/django-admin-flexlist
Project-URL: Source, https://github.com/rafael-frs-a/django-admin-flexlist
Keywords: django,admin,list view,app index,dashboard,toggle visibility,reorder elements,drag and drop,list_display
Classifier: Development Status :: 5 - Production/Stable
Classifier: Framework :: Django
Classifier: Intended Audience :: Developers
Classifier: License :: OSI Approved :: BSD License
Classifier: Programming Language :: Python :: 3
Classifier: Programming Language :: Python :: 3.10
Classifier: Programming Language :: Python :: 3.11
Classifier: Programming Language :: Python :: 3.12
Classifier: Framework :: Django :: 4.1
Classifier: Framework :: Django :: 4.2
Classifier: Framework :: Django :: 5.0
Classifier: Framework :: Django :: 5.1
Classifier: Framework :: Django :: 5.2
Requires-Python: >=3.10
License-File: LICENSE
Requires-Dist: django<5.3,>=4.1
Provides-Extra: dev
Requires-Dist: tox~=4.25; extra == "dev"
Requires-Dist: ipython~=8.34; extra == "dev"
Requires-Dist: black~=25.1; extra == "dev"
Requires-Dist: flake8~=7.2; extra == "dev"
Requires-Dist: isort~=6.0; extra == "dev"
Requires-Dist: mypy~=1.15; extra == "dev"
Requires-Dist: django-stubs[compatible-mypy]~=5.1; extra == "dev"
Requires-Dist: pytest~=8.3; extra == "dev"
Requires-Dist: pytest-playwright~=0.7; extra == "dev"
Dynamic: license-file
